handleget/error.py
handleget/info.py
handleget/load.py
handleget/parse.py
handleget/request.py
handleget/test.py
handleget/__init__.py
handleget-0.4.1.dist-info/DESCRIPTION.rst
handleget-0.4.1.dist-info/entry_points.txt
handleget-0.4.1.dist-info/METADATA
handleget-0.4.1.dist-info/metadata.json
handleget-0.4.1.dist-info/pbr.json
handleget-0.4.1.dist-info/RECORD
handleget-0.4.1.dist-info/top_level.txt
handleget-0.4.1.dist-info/WHEEL
