Metadata-Version: 2.0
Name: handleget
Version: 0.4.1
Summary: Get a handle on your online presence
Home-page: UNKNOWN
Author: Aaron Delaney
Author-email: devoxel@gmail.com
License: MIT
Keywords: web username
Platform: UNKNOWN
Requires-Dist: Click
